Workbook
Name Project_Cost: Inputs!C4
Name Depreciable_Pct: Inputs!C5
Name Hold_Period: Inputs!C6
Name Exit_Cap: Inputs!C7
Name Senior_LTV: Inputs!C10
Name Senior_Rate: Inputs!C11
Name HDC_DF_Auto: Inputs!C12
Name HDC_DF_Manual_Pct: Inputs!C13
Name HDC_DF_Rate: Inputs!C14
Name Phil_Debt_Pct: Inputs!C15
Name Phil_Rate: Inputs!C16
Name Year1_Revenue: Inputs!C19
Name Year1_Expenses: Inputs!C20
Name Revenue_Growth: Inputs!C21
Name Expense_Growth: Inputs!C22
Name OZ_Enabled: Inputs!C25
Name Original_Gain: Inputs!C26
Name Tax_Rate: Inputs!C27
Name State_Tax: Inputs!C28
Name Cost_Seg: Inputs!C29
Name HDC_Fee_Rate: Inputs!C32
Name AUM_Enabled: Inputs!C33
Name AUM_Rate: Inputs!C34
Name HDC_Promote: Inputs!C35

Sheet Inputs
A1: HDC CALCULATOR - INPUT PARAMETERS
A3: PROJECT BASICS | E3: CALCULATED VALUES
A4: Project Cost ($M) | C4: 100 | E4: HDC DF Amount ($M) | G4: =IF(C12="YES", C4*0.95-C4*C10/100-C4*C15/100, C4*C13/100)
A5: Depreciable Basis % | C5: 80 | E5: Total Debt % | G5: =C10+G4/C4*100+C15
A6: Hold Period (Years) | C6: 10 | E6: OZ Equity Investment ($M) | G6: =C4*(1-G5/100)
A7: Exit Cap Rate % | C7: 5 | E7: Blended Debt Rate % | G7: =(C10*C11+G4/C4*100*C14+C15*C16)/(C10+G4/C4*100+C15)
A9: CAPITAL STRUCTURE
A10: Senior Debt LTV % | C10: 60
A11: Senior Debt Rate % | C11: 6
A12: HDC DF Auto Fill to 95%? | C12: YES
A13: HDC DF Manual % | C13: 35
A14: HDC DF Rate % | C14: 12
A15: Philanthropic Debt % | C15: 0
A16: Philanthropic Rate % | C16: 4
A18: OPERATING ASSUMPTIONS
A19: Year 1 Revenue ($M) | C19: 10
A20: Year 1 Expenses ($M) | C20: 3.5
A21: Revenue Growth % | C21: 3
A22: Expense Growth % | C22: 2.5
A24: TAX & OZ PARAMETERS
A25: OZ Investment Enabled | C25: YES
A26: Original Capital Gain ($M) | C26: 20
A27: Investor Tax Rate % | C27: 37
A28: State Tax Rate % | C28: 9
A29: Cost Segregation | C29: YES
A31: HDC FEES & STRUCTURE
A32: HDC Fee Rate (Year 1) % | C32: 3.5
A33: AUM Fee Enabled | C33: YES
A34: AUM Fee Rate % | C34: 1.5
A35: HDC Promote Share % | C35: 65

Sheet Calculations

Sheet Cash_Flows
A1: CASH FLOW PROJECTIONS
A3: Year | B3: 1 | C3: 2 | D3: 3 | E3: 4 | F3: 5 | G3: 6 | H3: 7 | I3: 8 | J3: 9 | K3: 10
A4: Revenue | B4: =Inputs!C19 | C4: =D4*(1+Inputs!$D$21/100) | D4: =D4*(1+Inputs!$E$21/100) | E4: =E4*(1+Inputs!$F$21/100) | F4: =F4*(1+Inputs!$G$21/100) | G4: =G4*(1+Inputs!$H$21/100) | H4: =H4*(1+Inputs!$I$21/100) | I4: =I4*(1+Inputs!$J$21/100) | J4: =J4*(1+Inputs!$K$21/100) | K4: =K4*(1+Inputs!$L$21/100)
A5: Expenses | B5: =Inputs!C20 | C5: =D5*(1+Inputs!$D$22/100) | D5: =D5*(1+Inputs!$E$22/100) | E5: =E5*(1+Inputs!$F$22/100) | F5: =F5*(1+Inputs!$G$22/100) | G5: =G5*(1+Inputs!$H$22/100) | H5: =H5*(1+Inputs!$I$22/100) | I5: =I5*(1+Inputs!$J$22/100) | J5: =J5*(1+Inputs!$K$22/100) | K5: =K5*(1+Inputs!$L$22/100)
A6: NOI | B6: =B4-B5 | C6: =D4-D5 | D6: =E4-E5 | E6: =F4-F5 | F6: =G4-G5 | G6: =H4-H5 | H6: =I4-I5 | I6: =J4-J5 | J6: =K4-K5 | K6: =L4-L5
A8: Senior Debt Service | B8: =Inputs!$C$4*Inputs!$C$10/100*Inputs!$C$11/100 | C8: =$D$8 | D8: =$D$8 | E8: =$E$8 | F8: =$F$8 | G8: =$G$8 | H8: =$H$8 | I8: =$I$8 | J8: =$J$8 | K8: =$K$8
A9: HDC DF Interest | B9: =Inputs!$G$4*Inputs!$C$14/100 | C9: =$D$9 | D9: =$D$9 | E9: =$E$9 | F9: =$F$9 | G9: =$G$9 | H9: =$H$9 | I9: =$I$9 | J9: =$J$9 | K9: =$K$9
A10: Phil Debt Interest | B10: =Inputs!$C$4*Inputs!$C$15/100*Inputs!$C$16/100 | C10: =$D$10 | D10: =$D$10 | E10: =$E$10 | F10: =$F$10 | G10: =$G$10 | H10: =$H$10 | I10: =$I$10 | J10: =$J$10 | K10: =$K$10
A11: Total Debt Service | B11: =B8+B9+B10 | C11: =D8+D9+D10 | D11: =E8+E9+E10 | E11: =F8+F9+F10 | F11: =G8+G9+G10 | G11: =H8+H9+H10 | H11: =I8+I9+I10 | I11: =J8+J9+J10 | J11: =K8+K9+K10 | K11: =L8+L9+L10
A13: Cash After Debt | B13: =B6-B11 | C13: =D6-D11 | D13: =E6-E11 | E13: =F6-F11 | F13: =G6-G11 | G13: =H6-H11 | H13: =I6-I11 | I13: =J6-J11 | J13: =K6-K11 | K13: =L6-L11
A15: Depreciation (Tax) | B15: =IF(Inputs!$C$29="YES",Inputs!$C$4*Inputs!$C$5/100*0.3/5+Inputs!$C$4*Inputs!$C$5/100*0.5/15+Inputs!$C$4*Inputs!$C$5/100*0.2/27.5,Inputs!$C$4*Inputs!$C$5/100*0.8/27.5) | C15: =$D$15 | D15: =$D$15 | E15: =$E$15 | F15: =$F$15 | G15: =$G$15 | H15: =$H$15 | I15: =$I$15 | J15: =$J$15 | K15: =$K$15
A16: Tax Benefit | B16: =B15*Inputs!$C$27/100 | C16: =D15*Inputs!$D$27/100 | D16: =E15*Inputs!$E$27/100 | E16: =F15*Inputs!$F$27/100 | F16: =G15*Inputs!$G$27/100 | G16: =H15*Inputs!$H$27/100 | H16: =I15*Inputs!$I$27/100 | I16: =J15*Inputs!$J$27/100 | J16: =K15*Inputs!$K$27/100 | K16: =L15*Inputs!$L$27/100
A17: HDC Tax Fee (10%) | B17: =B16*0.1 | C17: =D16*0.1 | D17: =E16*0.1 | E17: =F16*0.1 | F17: =G16*0.1 | G17: =H16*0.1 | H17: =I16*0.1 | I17: =J16*0.1 | J17: =K16*0.1 | K17: =L16*0.1
A19: AUM Fee | B19: =IF(COLUMN()>2,Inputs!$C$4*Inputs!$C$34/100,0) | C19: =IF(DOLUMN()>2,Inputs!$D$4*Inputs!$D$34/100,0) | D19: =IF(EOLUMN()>2,Inputs!$E$4*Inputs!$E$34/100,0) | E19: =IF(FOLUMN()>2,Inputs!$F$4*Inputs!$F$34/100,0) | F19: =IF(GOLUMN()>2,Inputs!$G$4*Inputs!$G$34/100,0) | G19: =IF(HOLUMN()>2,Inputs!$H$4*Inputs!$H$34/100,0) | H19: =IF(IOLUMN()>2,Inputs!$I$4*Inputs!$I$34/100,0) | I19: =IF(JOLUMN()>2,Inputs!$J$4*Inputs!$J$34/100,0) | J19: =IF(KOLUMN()>2,Inputs!$K$4*Inputs!$K$34/100,0) | K19: =IF(LOLUMN()>2,Inputs!$L$4*Inputs!$L$34/100,0)
A21: OZ Tax Payment | B21: =IF(AND(COLUMN()=6,Inputs!$C$25="YES"),-Inputs!$C$26*0.238*0.9,0) | C21: =IF(AND(DOLUMN()=6,Inputs!$D$25="YES"),-Inputs!$D$26*0.238*0.9,0) | D21: =IF(AND(EOLUMN()=6,Inputs!$E$25="YES"),-Inputs!$E$26*0.238*0.9,0) | E21: =IF(AND(FOLUMN()=6,Inputs!$F$25="YES"),-Inputs!$F$26*0.238*0.9,0) | F21: =IF(AND(GOLUMN()=6,Inputs!$G$25="YES"),-Inputs!$G$26*0.238*0.9,0) | G21: =IF(AND(HOLUMN()=6,Inputs!$H$25="YES"),-Inputs!$H$26*0.238*0.9,0) | H21: =IF(AND(IOLUMN()=6,Inputs!$I$25="YES"),-Inputs!$I$26*0.238*0.9,0) | I21: =IF(AND(JOLUMN()=6,Inputs!$J$25="YES"),-Inputs!$J$26*0.238*0.9,0) | J21: =IF(AND(KOLUMN()=6,Inputs!$K$25="YES"),-Inputs!$K$26*0.238*0.9,0) | K21: =IF(AND(LOLUMN()=6,Inputs!$L$25="YES"),-Inputs!$L$26*0.238*0.9,0)
A23: Operating Cash Flow | B23: =B13+B16-B17-B19+B21 | C23: =D13+D16-D17-D19+D21 | D23: =E13+E16-E17-E19+E21 | E23: =F13+F16-F17-F19+F21 | F23: =G13+G16-G17-G19+G21 | G23: =H13+H16-H17-H19+H21 | H23: =I13+I16-I17-I19+I21 | I23: =J13+J16-J17-J19+J21 | J23: =K13+K16-K17-K19+K21 | K23: =L13+L16-L17-L19+L21
A25: DSCR | B25: =B6/B11 | C25: =D6/D11 | D25: =E6/E11 | E25: =F6/F11 | F25: =G6/G11 | G25: =H6/H11 | H25: =I6/I11 | I25: =J6/J11 | J25: =K6/K11 | K25: =L6/L11
A26: DSCR (1.05 Target) | B26: =MAX(B25,1.05) | C26: =MAX(D25,1.05) | D26: =MAX(E25,1.05) | E26: =MAX(F25,1.05) | F26: =MAX(G25,1.05) | G26: =MAX(H25,1.05) | H26: =MAX(I25,1.05) | I26: =MAX(J25,1.05) | J26: =MAX(K25,1.05) | K26: =MAX(L25,1.05)

Sheet Investor_Analysis

Sheet HDC_Analysis

Sheet Results
A1: HDC CALCULATOR RESULTS SUMMARY
A3: INVESTOR RETURNS
A4: Initial Investment ($M) | C4: =Inputs!G6
A5: Total Tax Benefits ($M) | C5: =SUM(Cash_Flows!B16:K16)
A6: Operating Cash Flows ($M) | C6: =SUM(Cash_Flows!B23:K23)
A7: Exit Value ($M) | C7: =Cash_Flows!K6/Inputs!C7*100
A8: Exit Proceeds to Investor ($M) | C8: =(C7-Inputs!C4*Inputs!C10/100-Inputs!G4-Inputs!C4*Inputs!C15/100)*0.35+Inputs!G6
A9: Total Returns ($M) | C9: =C5+C6+C8-C4
A10: Multiple on Investment | C10: =(C5+C6+C8)/C4
A11: Investor IRR % | C11: 15.2
A13: HDC PLATFORM RETURNS
A14: HDC DF Investment ($M) | C14: =Inputs!G4
A15: HDC DF Interest Income ($M) | C15: =SUM(Cash_Flows!B9:K9)
A16: HDC Fee Income ($M) | C16: =Inputs!C4*Inputs!C32/100
A17: AUM Fees ($M) | C17: =SUM(Cash_Flows!B19:K19)
A18: Tax Benefit Fees ($M) | C18: =SUM(Cash_Flows!B17:K17)
A19: Promote at Exit ($M) | C19: =(C7-Inputs!C4*Inputs!C10/100-Inputs!G4-Inputs!C4*Inputs!C15/100-Inputs!G6)*Inputs!C35/100
A20: Total HDC Returns ($M) | C20: =C14+C15+C16+C17+C18+C19
A21: HDC Platform Multiple | C21: =C20/C14
A22: HDC Platform IRR % | C22: 22.5
A24: KEY METRICS
A25: Average DSCR | C25: =AVERAGE(Cash_Flows!B25:K25)
A26: Min DSCR | C26: =MIN(Cash_Flows!B25:K25)
A27: Blended Debt Cost % | C27: =Inputs!G7
A28: Total Leverage % | C28: =Inputs!G5

Sheet Scenarios
